{"trial_id": "0", "hyperparameters": {"space": [{"class_name": "Choice", "config": {"name": "neurons", "default": 1024, "conditions": [], "values": [1024, 2048, 4096], "ordered": true}}], "values": {"neurons": 2048}}, "metrics": {"metrics": {"loss": {"direction": "min", "observations": [{"value": [0.4534089267253876], "step": 4}]}, "accuracy": {"direction": "max", "observations": [{"value": [0.8237907290458679], "step": 4}]}, "val_loss": {"direction": "min", "observations": [{"value": [0.4081859886646271], "step": 4}]}, "val_accuracy": {"direction": "max", "observations": [{"value": [0.8344630599021912], "step": 4}]}}}, "score": 0.8344630599021912, "best_step": 4, "status": "COMPLETED", "message": null}